README.md
retest
retest.yaml
setup.cfg
setup.py
spj
oiretest.egg-info/PKG-INFO
oiretest.egg-info/SOURCES.txt
oiretest.egg-info/dependency_links.txt
oiretest.egg-info/requires.txt
oiretest.egg-info/top_level.txt
plugin/_print.py
plugin/acm.py
plugin/block.py
plugin/default.py
plugin/easy.py
plugin/hitokoto.py
plugin/kewth.py
plugin/learnen.py
plugin/lmo.py
plugin/noac.py
plugin/robotic.py
plugin/score.py
plugin/zenity.py
source/__init__.py
source/config.py
source/file_fun.py
source/info.py
source/judge.py
source/learn.py
source/memory.py
source/plugin.py