Metadata-Version: 1.0
Name: oiretest
Version: 1.1.0
Summary: retest for OIer
Home-page: https://github.com/Kewth/retest
Author: Kewth
Author-email: Kewth.K.D@outlook.com
License: UNKNOWN
Platform: UNKNOWN
